pertinence/__init__.py
pertinence-0.0.1.dev1.dist-info/LICENSE
pertinence-0.0.1.dev1.dist-info/METADATA
pertinence-0.0.1.dev1.dist-info/WHEEL
pertinence-0.0.1.dev1.dist-info/top_level.txt
pertinence-0.0.1.dev1.dist-info/RECORD
