Metadata-Version: 2.1
Name: pertinence
Version: 0.0.1.dev1
Summary: A Python library for training neural search models
Author-email: Ikuya Yamada <ikuya@ousia.jp>
License: Copyright 2017 Studio Ousia
Classifier: Development Status :: 1 - Planning
Classifier: License :: OSI Approved :: Apache Software License
Classifier: Programming Language :: Python
Classifier: Programming Language :: Python :: 3
Requires-Python: >=3.7
License-File: LICENSE
